wscodec/__init__.py
wscodec/encoder/__init__.py
wscodec/encoder/pyencoder/unitc.py
wscodec/encoder/pyencoder/demi_builder.py
wscodec/encoder/pyencoder/sample_builder.py
wscodec/encoder/pyencoder/encoderfactory.py
wscodec/encoder/pyencoder/ndef_builder.py
wscodec/encoder/pyencoder/pairhist_builder.py
wscodec/encoder/pyencoder/eeprom.py
wscodec/encoder/pyencoder/instrumented.py
wscodec/encoder/pyencoder/__init__.py
wscodec/encoder/pyencoder/sharedobj/ndefpy.abi3.so
wscodec/encoder/pyencoder/sharedobj/pairhistpy.abi3.so
wscodec/encoder/pyencoder/sharedobj/samplepy.abi3.so
wscodec/encoder/pyencoder/sharedobj/demipy.abi3.so
wscodec/encoder/pyencoder/sharedobj/__init__.py
wscodec/decoder/b64decode.py
wscodec/decoder/decoderfactory.py
wscodec/decoder/circularbuffer.py
wscodec/decoder/samples.py
wscodec/decoder/status.py
wscodec/decoder/hdc2021.py
wscodec/decoder/pairs.py
wscodec/decoder/__init__.py
wscodec/decoder/exceptions.py
tests/test_status.py
tests/test_tsample.py
tests/conftest.py
tests/test_ndef.py
tests/test_pairhist.py
tests/test_trhsample.py
tests/test_minuteoffset.py
tests/__init__.py
tests/test_cursorpos.py
cuplcodec-2.1.0.dist-info/LICENSE
cuplcodec-2.1.0.dist-info/METADATA
cuplcodec-2.1.0.dist-info/RECORD
cuplcodec-2.1.0.dist-info/WHEEL
cuplcodec-2.1.0.dist-info/top_level.txt
