Metadata-Version: 2.1
Name: cuplcodec
Version: 2.1.0
Summary: Package for creating and decoding URLs that contain temperature and humidity samples.
Home-page: https://github.com/cuplsensor/cuplcodec
Author: Malcolm Mackay
Author-email: malcolm@plotsensor.com
License: UNKNOWN
Platform: UNKNOWN
Classifier: Development Status :: 5 - Production/Stable
Classifier: Programming Language :: Python :: 3
Classifier: License :: OSI Approved :: GNU General Public License v3 (GPLv3)
Classifier: Natural Language :: English
Classifier: Operating System :: POSIX :: Linux
